tuco/__init__.py
tuco/base.py
tuco/decorators.py
tuco/exceptions.py
tuco/graph_builder.py
tuco/meta.py
tuco/properties.py
tuco/locks/__init__.py
tuco/locks/base.py
tuco/locks/memory.py
tuco/locks/redis.py
tuco-0.2.0.dist-info/DESCRIPTION.rst
tuco-0.2.0.dist-info/METADATA
tuco-0.2.0.dist-info/RECORD
tuco-0.2.0.dist-info/WHEEL
tuco-0.2.0.dist-info/metadata.json
tuco-0.2.0.dist-info/top_level.txt
