Metadata-Version: 2.0
Name: tuco
Version: 0.2.0
Summary: A simple class based finite state machine with parsing time validation
Home-page: https://github.com/eatfirst/python-tuco
Author: EatFirst
Author-email: it+opensource@eatfirst.com
License: MIT license
Platform: UNKNOWN
Classifier: Development Status :: 5 - Production/Stable
Classifier: Intended Audience :: Developers
Classifier: License :: OSI Approved :: MIT License
Classifier: Operating System :: Unix
Classifier: Operating System :: POSIX
Classifier: Operating System :: Microsoft :: Windows
Classifier: Programming Language :: Python
Classifier: Programming Language :: Python :: 3.4
Classifier: Programming Language :: Python :: 3.5
Classifier: Programming Language :: Python :: 3.6
Classifier: Programming Language :: Python :: Implementation :: CPython
Classifier: Programming Language :: Python :: Implementation :: PyPy
Classifier: Topic :: Utilities
Requires-Dist: pytz
Requires-Dist: typing
Provides-Extra: graph
Requires-Dist: graphviz (>=0.8.1); extra == 'graph'
Provides-Extra: redis
Requires-Dist: redis (>=2.10); extra == 'redis'
